pyri/__init__.py
pyri-0.0.1.dist-info/METADATA
pyri-0.0.1.dist-info/RECORD
pyri-0.0.1.dist-info/WHEEL
pyri-0.0.1.dist-info/top_level.txt
