Metadata-Version: 2.1
Name: pyri
Version: 0.0.1
Summary: The pyri package reads a ...
Home-page: https://github.com/pypa/example-project
Author: pyq
Author-email: vcsqlt@gmail.com
License: UNKNOWN
Platform: UNKNOWN
Classifier: Programming Language :: Python :: 3
Classifier: License :: OSI Approved :: MIT License
Classifier: Operating System :: OS Independent
